{"date":"2024-05-23T15:00:30.829Z","courseId":"17","assignment":"AP-Spring03-CA6","trace":{"version":705,"content":"\n#include \"../includes/lesson.hpp\"\n\nLesson::Lesson(LessonStruct ls, int lessonID)\n{\n    courseName = ls.courseName;\n    profName = ls.profName;\n    courseId = ls.courseId;\n    profId = ls.profId;\n    capacity = ls.capacity;\n    time.weekDay = ls.weekDay;\n    time.startTime = ls.startTime;\n    time.endTime = ls.endTime;\n    date = ls.date;\n    classNumber = ls.classNumber;\n    lessonID = ls.lessonID;\n}\n\nLesson::~Lesson()\n{\n}\n\nstring  Lesson::get_course_name(){return courseName;};\nstring  Lesson::get_prof_name(){return profName;};\nstring  Lesson::get_course_id(){return courseId;};\nstring Lesson::get_capacity(){return capacity;};\nstring  Lesson::get_week_day(){return time.weekDay;};\nstring  Lesson::get_start_time(){return time.startTime;};\nstring  Lesson::get_end_time(){return time.endTime;};\nstring  Lesson::get_class_num(){return classNumber;};\nstring Lesson::get_date(){return date;};\n","filename":"/home/ali3ad3ghi/project6-f1/UTMS-Website/src/lesson.cpp","identifier":"Text Change","lineCount":32,"languageId":"cpp"},"failed":false}